nju_digital/ex3/top.v
module top(
	input [2:0] op,
	input [3:0] in_x, in_y,
	output reg [3:0] out_s,
	output reg overflow, out_c, zero
);
	reg [3:0] t_add_y = ( 4'b1111^in_y );  
	always @(*)
	begin
		case(op)
			3'b000:
			begin
				{out_c, out_s} = in_x + in_y;
				zero = ~(| out_s);
				overflow = (in_x[3] == in_y[3]) && (out_s[3] != in_x[3]);
			end
			3'b001:
			begin
				{out_c, out_s} = in_x + t_add_y + 1'b1;
				zero = ~(| out_s);
				overflow = (in_x[3] == t_add_y[3]) && (out_s[3] != in_x[3]);
			end
			3'b010:
			begin
				out_s = ~in_x;
				zero = ~(| out_s);
				out_c = 0;
				overflow = 0;
			end
			3'b011:
			begin
				out_s = in_x & in_y;
				zero = ~(| out_s);
				out_c = 0;
				overflow = 0;
			end
			3'b100:
			begin
				out_s = in_x | in_y;
				zero = ~(| out_s);
				out_c = 0;
				overflow = 0;
			end
			3'b101:
			begin
				out_s = in_x ^ in_y;
				zero = ~(| out_s);
				out_c = 0;
				overflow = 0;
			end
			3'b110:
			begin
				if (in_x[3] == 1 && in_y[3] == 0)
					out_s = 1;
				else if (in_x[3] == 0 && in_y[3] == 1)
					out_s = 0;
				else
					out_s = in_x < in_y ? 1 : 0;
				zero = out_s == 0 ? 1 : 0;
				out_c = 0;
				overflow = 0;
			end
			default:
			begin
				if (in_x == in_y)
					out_s = 1;
				else
					out_s = 0;
				zero = out_s == 0 ? 1 : 0;
				out_c = 0;
				overflow = 0;
			end
		endcase
	end

	endmodule

nju_digital/ex3/dump.vcd
$version Generated by VerilatedVcd $end
$timescale 1s $end

 $scope module TOP $end
  $var wire  4 $ in_x [3:0] $end
  $var wire  4 % in_y [3:0] $end
  $var wire  3 # op [2:0] $end
  $var wire  1 ( out_c $end
  $var wire  4 & out_s [3:0] $end
  $var wire  1 ' overflow $end
  $var wire  1 ) zero $end
  $scope module top $end
   $var wire  4 $ in_x [3:0] $end
   $var wire  4 % in_y [3:0] $end
   $var wire  3 # op [2:0] $end
   $var wire  1 ( out_c $end
   $var wire  4 & out_s [3:0] $end
   $var wire  1 ' overflow $end
   $var wire  4 * t_add_y [3:0] $end
   $var wire  1 ) zero $end
  $upscope $end
 $upscope $end
$enddefinitions $end


#1
b000 #
b1000 $
b0111 %
b1111 &
0'
1(
0)
b1000 *
#2
b1001 %
b0001 &
1'
b0110 *
#3
b0011 $
b0111 %
b1010 &
0(
b1000 *
#4
b0001 $
b0011 %
b0100 &
0'
b1100 *
#5
b1111 $
b1111 %
b1110 &
1(
b0000 *
#6
b001 #
b1000 $
b0111 %
b0001 &
1'
0(
b1000 *
#7
b1001 %
b1111 &
0'
1(
b0110 *
#8
b0011 $
b0111 %
b1100 &
0(
b1000 *
#9
b0111 $
b0011 %
b0100 &
1(
b1100 *
#10
b1111 $
b1111 %
b0000 &
0(
1)
b0000 *
#11
b010 #
b1000 $
b0111 %
b0111 &
0)
b1000 *
#12
b0001 $
b0011 %
b1110 &
b1100 *
#13
b1111 $
b1111 %
b0000 &
1)
b0000 *
#14
b011 #
b1000 $
b0111 %
b1000 *
#15
b1001 %
b1000 &
0)
b0110 *
#16
b0011 $
b0111 %
b0011 &
b1000 *
#17
b0001 $
b0011 %
b0001 &
b1100 *
#18
b1111 $
b1111 %
b1111 &
b0000 *
#19
b100 #
b1000 $
b0111 %
b1000 *
#20
b1001 %
b1001 &
b0110 *
#21
b0011 $
b0111 %
b0111 &
b1000 *
#22
b0001 $
b0011 %
b0011 &
b1100 *
#23
b1111 $
b1111 %
b1111 &
b0000 *
#24
b101 #
b1000 $
b0111 %
b1000 *
#25
b1001 %
b0001 &
b0110 *
#26
b0011 $
b0111 %
b0100 &
b1000 *
#27
b0001 $
b0011 %
b0010 &
b1100 *
#28
b1111 $
b1111 %
b0000 &
1)
b0000 *
#29
b110 #
b1000 $
b0111 %
b0001 &
0)
b1000 *
#30
b0110 $
b1001 %
b0000 &
1)
b0110 *
#31
b1101 $
#32
b0001 $
b0011 %
b0001 &
0)
b1100 *
#33
b0001 %
b0000 &
1)
b1110 *
#34
b111 #
b1000 $
b0111 %
b1000 *
#35
b0011 $
#36
b0001 $
b0001 %
b0001 &
0)
b1110 *
#37
b1111 $
b1111 %
b0000 *
