nju_digital/fpga/lab2/vsrc/bcd7seg.v
module bcd7seg(
  input  [3:0] b,
  output reg [6:0] h
);

  always @(*) begin
	  case (b)
		4'd1: h = 7'b1111001;
		4'd2: h = 7'b0100100;
		4'd3: h = 7'b0110000;
		4'd4: h = 7'b0011001;
		4'd5: h = 7'b0010010;
		4'd6: h = 7'b0000010;
		4'd7: h = 7'b1111000;
		4'd8: h = 7'b0000000;
		4'd9: h = 7'b0010000;
		4'ha: h = 7'b0001000;
		4'hb: h = 7'b0000011;
		4'hc: h = 7'b1000110;
		4'hd: h = 7'b0100001;
		4'he: h = 7'b0000110;
		4'hf: h = 7'b0001110;
		default: h = 7'b1000000;
	endcase
  end
endmodule

nju_digital/fpga/lab6/vsrc/top.v
module top(
    input clk,
    input[7:0] din,
    output[6:0] dout1, dout0
);
    reg [7:0]dout = din;
	reg [7:0]temp = din;
    integer i = 0;
    always@(posedge clk or din)begin
		if(din == temp)begin
          if(dout == 8'b0) dout <= din; 
          else begin
              if(i == 255) dout <= din;
              else begin
                  dout <= {dout[4]^dout[3]^dout[2]^dout[1] ,dout[7:1]};
                  i = i + 1;
              end
          end
	    end
		else begin
			dout <= din;
			temp <= din;
		end
    end
    bcd7seg i1(.b(dout[7:4]), .h(dout1));
    bcd7seg i0(.b(dout[3:0]), .h(dout0));
endmodule

nju_digital/ex6/LFSR/dump.vcd
$version Generated by VerilatedVcd $end
$timescale 1s $end

 $scope module TOP $end
  $var wire  1 ( clk $end
  $var wire  8 ) din [7:0] $end
  $var wire  7 + dout0 [6:0] $end
  $var wire  7 * dout1 [6:0] $end
  $scope module top $end
   $var wire  1 ( clk $end
   $var wire  8 ) din [7:0] $end
   $var wire  8 # dout [7:0] $end
   $var wire  7 + dout0 [6:0] $end
   $var wire  7 * dout1 [6:0] $end
   $var wire 32 % i [31:0] $end
   $var wire  8 $ temp [7:0] $end
   $scope module i0 $end
    $var wire  4 & b [3:0] $end
    $var wire  7 + h [6:0] $end
   $upscope $end
   $scope module i1 $end
    $var wire  4 ' b [3:0] $end
    $var wire  7 * h [6:0] $end
   $upscope $end
  $upscope $end
 $upscope $end
$enddefinitions $end


#1
b10011000 #
b00110000 $
b00000000000000000000000000000001 %
b1000 &
b1001 '
0(
b00110000 )
b0010000 *
b0000000 +
#2
b01001100 #
b00000000000000000000000000000010 %
b1100 &
b0100 '
1(
b0011001 *
b1000110 +
#3
0(
#4
b00100110 #
b00000000000000000000000000000011 %
b0110 &
b0010 '
1(
b0100100 *
b0000010 +
#5
0(
#6
b00010011 #
b00000000000000000000000000000100 %
b0011 &
b0001 '
1(
b1111001 *
b0110000 +
#7
0(
#8
b00001001 #
b00000000000000000000000000000101 %
b1001 &
b0000 '
1(
b1000000 *
b0010000 +
#9
0(
#10
b10000100 #
b00000000000000000000000000000110 %
b0100 &
b1000 '
1(
b0000000 *
b0011001 +
#11
0(
#12
b11000010 #
b00000000000000000000000000000111 %
b0010 &
b1100 '
1(
b1000110 *
b0100100 +
#13
0(
#14
b11100001 #
b00000000000000000000000000001000 %
b0001 &
b1110 '
1(
b0000110 *
b1111001 +
#15
0(
#16
b01110000 #
b00000000000000000000000000001001 %
b0000 &
b0111 '
1(
b1111000 *
b1000000 +
#17
0(
#18
b10111000 #
b00000000000000000000000000001010 %
b1000 &
b1011 '
1(
b0000011 *
b0000000 +
#19
0(
#20
b01011100 #
b00000000000000000000000000001011 %
b1100 &
b0101 '
1(
b0010010 *
b1000110 +
#21
0(
#22
b10101110 #
b00000000000000000000000000001100 %
b1110 &
b1010 '
1(
b0001000 *
b0000110 +
#23
0(
#24
b11010111 #
b00000000000000000000000000001101 %
b0111 &
b1101 '
1(
b0100001 *
b1111000 +
#25
0(
#26
b11101011 #
b00000000000000000000000000001110 %
b1011 &
b1110 '
1(
b0000110 *
b0000011 +
#27
0(
#28
b01110101 #
b00000000000000000000000000001111 %
b0101 &
b0111 '
1(
b1111000 *
b0010010 +
#29
0(
#30
b00111010 #
b00000000000000000000000000010000 %
b1010 &
b0011 '
1(
b0110000 *
b0001000 +
#31
0(
#32
b10011101 #
b00000000000000000000000000010001 %
b1101 &
b1001 '
1(
b0010000 *
b0100001 +
#33
0(
#34
b11001110 #
b00000000000000000000000000010010 %
b1110 &
b1100 '
1(
b1000110 *
b0000110 +
#35
0(
#36
b11100111 #
b00000000000000000000000000010011 %
b0111 &
b1110 '
1(
b0000110 *
b1111000 +
#37
0(
#38
b01110011 #
b00000000000000000000000000010100 %
b0011 &
b0111 '
1(
b1111000 *
b0110000 +
#39
0(
#40
b00111001 #
b00000000000000000000000000010101 %
b1001 &
b0011 '
1(
b0110000 *
b0010000 +
#41
0(
#42
b00011100 #
b00000000000000000000000000010110 %
b1100 &
b0001 '
1(
b1111001 *
b1000110 +
#43
0(
#44
b10001110 #
b00000000000000000000000000010111 %
b1110 &
b1000 '
1(
b0000000 *
b0000110 +
#45
0(
#46
b11000111 #
b00000000000000000000000000011000 %
b0111 &
b1100 '
1(
b1000110 *
b1111000 +
#47
0(
#48
b01100011 #
b00000000000000000000000000011001 %
b0011 &
b0110 '
1(
b0000010 *
b0110000 +
#49
0(
#50
b10110001 #
b00000000000000000000000000011010 %
b0001 &
b1011 '
1(
b0000011 *
b1111001 +
#51
0(
#52
b11011000 #
b00000000000000000000000000011011 %
b1000 &
b1101 '
1(
b0100001 *
b0000000 +
#53
0(
#54
b01101100 #
b00000000000000000000000000011100 %
b1100 &
b0110 '
1(
b0000010 *
b1000110 +
#55
0(
#56
b00110110 #
b00000000000000000000000000011101 %
b0110 &
b0011 '
1(
b0110000 *
b0000010 +
#57
0(
#58
b10011011 #
b00000000000000000000000000011110 %
b1011 &
b1001 '
1(
b0010000 *
b0000011 +
#59
0(
#60
b11001101 #
b00000000000000000000000000011111 %
b1101 &
b1100 '
1(
b1000110 *
b0100001 +
#61
0(
#62
b01100110 #
b00000000000000000000000000100000 %
b0110 &
b0110 '
1(
b0000010 *
b0000010 +
#63
0(
#64
b00110011 #
b00000000000000000000000000100001 %
b0011 &
b0011 '
1(
b0110000 *
b0110000 +
#65
0(
#66
b00011001 #
b00000000000000000000000000100010 %
b1001 &
b0001 '
1(
b1111001 *
b0010000 +
#67
0(
#68
b00001100 #
b00000000000000000000000000100011 %
b1100 &
b0000 '
1(
b1000000 *
b1000110 +
#69
0(
#70
b00000110 #
b00000000000000000000000000100100 %
b0110 &
1(
b0000010 +
#71
0(
#72
b00000011 #
b00000000000000000000000000100101 %
b0011 &
1(
b0110000 +
#73
0(
#74
b10000001 #
b00000000000000000000000000100110 %
b0001 &
b1000 '
1(
b0000000 *
b1111001 +
#75
0(
#76
b01000000 #
b00000000000000000000000000100111 %
b0000 &
b0100 '
1(
b0011001 *
b1000000 +
#77
0(
#78
b00100000 #
b00000000000000000000000000101000 %
b0010 '
1(
b0100100 *
#79
0(
#80
b00010000 #
b00000000000000000000000000101001 %
b0001 '
1(
b1111001 *
#81
0(
#82
b10001000 #
b00000000000000000000000000101010 %
b1000 &
b1000 '
1(
b0000000 *
b0000000 +
#83
0(
#84
b11000100 #
b00000000000000000000000000101011 %
b0100 &
b1100 '
1(
b1000110 *
b0011001 +
#85
0(
#86
b11100010 #
b00000000000000000000000000101100 %
b0010 &
b1110 '
1(
b0000110 *
b0100100 +
#87
0(
#88
b11110001 #
b00000000000000000000000000101101 %
b0001 &
b1111 '
1(
b0001110 *
b1111001 +
#89
0(
#90
b11111000 #
b00000000000000000000000000101110 %
b1000 &
1(
b0000000 +
#91
0(
#92
b01111100 #
b00000000000000000000000000101111 %
b1100 &
b0111 '
1(
b1111000 *
b1000110 +
#93
0(
#94
b10111110 #
b00000000000000000000000000110000 %
b1110 &
b1011 '
1(
b0000011 *
b0000110 +
#95
0(
#96
b01011111 #
b00000000000000000000000000110001 %
b1111 &
b0101 '
1(
b0010010 *
b0001110 +
#97
0(
#98
b00101111 #
b00000000000000000000000000110010 %
b0010 '
1(
b0100100 *
#99
0(
#100
b10010111 #
b00000000000000000000000000110011 %
b0111 &
b1001 '
1(
b0010000 *
b1111000 +
#101
0(
#102
b11001011 #
b00000000000000000000000000110100 %
b1011 &
b1100 '
1(
b1000110 *
b0000011 +
#103
0(
#104
b01100101 #
b00000000000000000000000000110101 %
b0101 &
b0110 '
1(
b0000010 *
b0010010 +
#105
0(
#106
b10110010 #
b00000000000000000000000000110110 %
b0010 &
b1011 '
1(
b0000011 *
b0100100 +
#107
0(
#108
b01011001 #
b00000000000000000000000000110111 %
b1001 &
b0101 '
1(
b0010010 *
b0010000 +
#109
0(
#110
b00101100 #
b00000000000000000000000000111000 %
b1100 &
b0010 '
1(
b0100100 *
b1000110 +
#111
0(
#112
b00010110 #
b00000000000000000000000000111001 %
b0110 &
b0001 '
1(
b1111001 *
b0000010 +
#113
0(
#114
b10001011 #
b00000000000000000000000000111010 %
b1011 &
b1000 '
1(
b0000000 *
b0000011 +
#115
0(
#116
b01000101 #
b00000000000000000000000000111011 %
b0101 &
b0100 '
1(
b0011001 *
b0010010 +
#117
0(
#118
b10100010 #
b00000000000000000000000000111100 %
b0010 &
b1010 '
1(
b0001000 *
b0100100 +
#119
0(
#120
b11010001 #
b00000000000000000000000000111101 %
b0001 &
b1101 '
1(
b0100001 *
b1111001 +
#121
0(
#122
b11101000 #
b00000000000000000000000000111110 %
b1000 &
b1110 '
1(
b0000110 *
b0000000 +
#123
0(
#124
b11110100 #
b00000000000000000000000000111111 %
b0100 &
b1111 '
1(
b0001110 *
b0011001 +
#125
0(
#126
b01111010 #
b00000000000000000000000001000000 %
b1010 &
b0111 '
1(
b1111000 *
b0001000 +
#127
0(
#128
b10111101 #
b00000000000000000000000001000001 %
b1101 &
b1011 '
1(
b0000011 *
b0100001 +
#129
0(
#130
b11011110 #
b00000000000000000000000001000010 %
b1110 &
b1101 '
1(
b0100001 *
b0000110 +
#131
0(
#132
b01101111 #
b00000000000000000000000001000011 %
b1111 &
b0110 '
1(
b0000010 *
b0001110 +
#133
0(
#134
b10110111 #
b00000000000000000000000001000100 %
b0111 &
b1011 '
1(
b0000011 *
b1111000 +
#135
0(
#136
b11011011 #
b00000000000000000000000001000101 %
b1011 &
b1101 '
1(
b0100001 *
b0000011 +
#137
0(
#138
b11101101 #
b00000000000000000000000001000110 %
b1101 &
b1110 '
1(
b0000110 *
b0100001 +
#139
0(
#140
b01110110 #
b00000000000000000000000001000111 %
b0110 &
b0111 '
1(
b1111000 *
b0000010 +
#141
0(
#142
b10111011 #
b00000000000000000000000001001000 %
b1011 &
b1011 '
1(
b0000011 *
b0000011 +
#143
0(
#144
b11011101 #
b00000000000000000000000001001001 %
b1101 &
b1101 '
1(
b0100001 *
b0100001 +
#145
0(
#146
b11101110 #
b00000000000000000000000001001010 %
b1110 &
b1110 '
1(
b0000110 *
b0000110 +
#147
0(
#148
b11110111 #
b00000000000000000000000001001011 %
b0111 &
b1111 '
1(
b0001110 *
b1111000 +
#149
0(
#150
b11111011 #
b00000000000000000000000001001100 %
b1011 &
1(
b0000011 +
#151
0(
#152
b11111101 #
b00000000000000000000000001001101 %
b1101 &
1(
b0100001 +
#153
0(
#154
b11111110 #
b00000000000000000000000001001110 %
b1110 &
1(
b0000110 +
#155
0(
#156
b01111111 #
b00000000000000000000000001001111 %
b1111 &
b0111 '
1(
b1111000 *
b0001110 +
#157
0(
#158
b00111111 #
b00000000000000000000000001010000 %
b0011 '
1(
b0110000 *
#159
0(
#160
b00011111 #
b00000000000000000000000001010001 %
b0001 '
1(
b1111001 *
#161
0(
#162
b00001111 #
b00000000000000000000000001010010 %
b0000 '
1(
b1000000 *
#163
0(
#164
b10000111 #
b00000000000000000000000001010011 %
b0111 &
b1000 '
1(
b0000000 *
b1111000 +
#165
0(
#166
b01000011 #
b00000000000000000000000001010100 %
b0011 &
b0100 '
1(
b0011001 *
b0110000 +
#167
0(
#168
b10100001 #
b00000000000000000000000001010101 %
b0001 &
b1010 '
1(
b0001000 *
b1111001 +
#169
0(
#170
b01010000 #
b00000000000000000000000001010110 %
b0000 &
b0101 '
1(
b0010010 *
b1000000 +
#171
0(
#172
b10101000 #
b00000000000000000000000001010111 %
b1000 &
b1010 '
1(
b0001000 *
b0000000 +
#173
0(
#174
b11010100 #
b00000000000000000000000001011000 %
b0100 &
b1101 '
1(
b0100001 *
b0011001 +
#175
0(
#176
b01101010 #
b00000000000000000000000001011001 %
b1010 &
b0110 '
1(
b0000010 *
b0001000 +
#177
0(
#178
b00110101 #
b00000000000000000000000001011010 %
b0101 &
b0011 '
1(
b0110000 *
b0010010 +
#179
0(
#180
b00011010 #
b00000000000000000000000001011011 %
b1010 &
b0001 '
1(
b1111001 *
b0001000 +
#181
0(
#182
b10001101 #
b00000000000000000000000001011100 %
b1101 &
b1000 '
1(
b0000000 *
b0100001 +
#183
0(
#184
b01000110 #
b00000000000000000000000001011101 %
b0110 &
b0100 '
1(
b0011001 *
b0000010 +
#185
0(
#186
b00100011 #
b00000000000000000000000001011110 %
b0011 &
b0010 '
1(
b0100100 *
b0110000 +
#187
0(
#188
b10010001 #
b00000000000000000000000001011111 %
b0001 &
b1001 '
1(
b0010000 *
b1111001 +
#189
0(
#190
b11001000 #
b00000000000000000000000001100000 %
b1000 &
b1100 '
1(
b1000110 *
b0000000 +
#191
0(
#192
b11100100 #
b00000000000000000000000001100001 %
b0100 &
b1110 '
1(
b0000110 *
b0011001 +
#193
0(
#194
b11110010 #
b00000000000000000000000001100010 %
b0010 &
b1111 '
1(
b0001110 *
b0100100 +
#195
0(
#196
b01111001 #
b00000000000000000000000001100011 %
b1001 &
b0111 '
1(
b1111000 *
b0010000 +
#197
0(
#198
b00111100 #
b00000000000000000000000001100100 %
b1100 &
b0011 '
1(
b0110000 *
b1000110 +
#199
0(
#200
b10011110 #
b00000000000000000000000001100101 %
b1110 &
b1001 '
1(
b0010000 *
b0000110 +
#201
0(
#202
b01001111 #
b00000000000000000000000001100110 %
b1111 &
b0100 '
1(
b0011001 *
b0001110 +
#203
0(
#204
b10100111 #
b00000000000000000000000001100111 %
b0111 &
b1010 '
1(
b0001000 *
b1111000 +
#205
0(
#206
b01010011 #
b00000000000000000000000001101000 %
b0011 &
b0101 '
1(
b0010010 *
b0110000 +
#207
0(
#208
b00101001 #
b00000000000000000000000001101001 %
b1001 &
b0010 '
1(
b0100100 *
b0010000 +
#209
0(
#210
b10010100 #
b00000000000000000000000001101010 %
b0100 &
b1001 '
1(
b0010000 *
b0011001 +
#211
0(
#212
b01001010 #
b00000000000000000000000001101011 %
b1010 &
b0100 '
1(
b0011001 *
b0001000 +
#213
0(
#214
b00100101 #
b00000000000000000000000001101100 %
b0101 &
b0010 '
1(
b0100100 *
b0010010 +
#215
0(
#216
b10010010 #
b00000000000000000000000001101101 %
b0010 &
b1001 '
1(
b0010000 *
b0100100 +
#217
0(
#218
b01001001 #
b00000000000000000000000001101110 %
b1001 &
b0100 '
1(
b0011001 *
b0010000 +
#219
0(
#220
b10100100 #
b00000000000000000000000001101111 %
b0100 &
b1010 '
1(
b0001000 *
b0011001 +
#221
0(
#222
b11010010 #
b00000000000000000000000001110000 %
b0010 &
b1101 '
1(
b0100001 *
b0100100 +
#223
0(
#224
b01101001 #
b00000000000000000000000001110001 %
b1001 &
b0110 '
1(
b0000010 *
b0010000 +
#225
0(
#226
b10110100 #
b00000000000000000000000001110010 %
b0100 &
b1011 '
1(
b0000011 *
b0011001 +
#227
0(
#228
b01011010 #
b00000000000000000000000001110011 %
b1010 &
b0101 '
1(
b0010010 *
b0001000 +
#229
0(
#230
b10101101 #
b00000000000000000000000001110100 %
b1101 &
b1010 '
1(
b0001000 *
b0100001 +
#231
0(
#232
b01010110 #
b00000000000000000000000001110101 %
b0110 &
b0101 '
1(
b0010010 *
b0000010 +
#233
0(
#234
b10101011 #
b00000000000000000000000001110110 %
b1011 &
b1010 '
1(
b0001000 *
b0000011 +
#235
0(
#236
b01010101 #
b00000000000000000000000001110111 %
b0101 &
b0101 '
1(
b0010010 *
b0010010 +
#237
0(
#238
b00101010 #
b00000000000000000000000001111000 %
b1010 &
b0010 '
1(
b0100100 *
b0001000 +
#239
0(
#240
b00010101 #
b00000000000000000000000001111001 %
b0101 &
b0001 '
1(
b1111001 *
b0010010 +
#241
0(
#242
b00001010 #
b00000000000000000000000001111010 %
b1010 &
b0000 '
1(
b1000000 *
b0001000 +
#243
0(
#244
b00000101 #
b00000000000000000000000001111011 %
b0101 &
1(
b0010010 +
#245
0(
#246
b10000010 #
b00000000000000000000000001111100 %
b0010 &
b1000 '
1(
b0000000 *
b0100100 +
#247
0(
#248
b11000001 #
b00000000000000000000000001111101 %
b0001 &
b1100 '
1(
b1000110 *
b1111001 +
#249
0(
#250
b01100000 #
b00000000000000000000000001111110 %
b0000 &
b0110 '
1(
b0000010 *
b1000000 +
#251
0(
#252
b00110000 #
b00000000000000000000000001111111 %
b0011 '
1(
b0110000 *
#253
0(
#254
b10011000 #
b00000000000000000000000010000000 %
b1000 &
b1001 '
1(
b0010000 *
b0000000 +
#255
0(
#256
b01001100 #
b00000000000000000000000010000001 %
b1100 &
b0100 '
1(
b0011001 *
b1000110 +
#257
0(
#258
b00100110 #
b00000000000000000000000010000010 %
b0110 &
b0010 '
1(
b0100100 *
b0000010 +
#259
0(
#260
b00010011 #
b00000000000000000000000010000011 %
b0011 &
b0001 '
1(
b1111001 *
b0110000 +
#261
0(
#262
b00001001 #
b00000000000000000000000010000100 %
b1001 &
b0000 '
1(
b1000000 *
b0010000 +
#263
0(
#264
b10000100 #
b00000000000000000000000010000101 %
b0100 &
b1000 '
1(
b0000000 *
b0011001 +
#265
0(
#266
b11000010 #
b00000000000000000000000010000110 %
b0010 &
b1100 '
1(
b1000110 *
b0100100 +
#267
0(
#268
b11100001 #
b00000000000000000000000010000111 %
b0001 &
b1110 '
1(
b0000110 *
b1111001 +
#269
0(
#270
b01110000 #
b00000000000000000000000010001000 %
b0000 &
b0111 '
1(
b1111000 *
b1000000 +
#271
0(
#272
b10111000 #
b00000000000000000000000010001001 %
b1000 &
b1011 '
1(
b0000011 *
b0000000 +
#273
0(
#274
b01011100 #
b00000000000000000000000010001010 %
b1100 &
b0101 '
1(
b0010010 *
b1000110 +
#275
0(
#276
b10101110 #
b00000000000000000000000010001011 %
b1110 &
b1010 '
1(
b0001000 *
b0000110 +
#277
0(
#278
b11010111 #
b00000000000000000000000010001100 %
b0111 &
b1101 '
1(
b0100001 *
b1111000 +
#279
0(
#280
b11101011 #
b00000000000000000000000010001101 %
b1011 &
b1110 '
1(
b0000110 *
b0000011 +
#281
0(
#282
b01110101 #
b00000000000000000000000010001110 %
b0101 &
b0111 '
1(
b1111000 *
b0010010 +
#283
0(
#284
b00111010 #
b00000000000000000000000010001111 %
b1010 &
b0011 '
1(
b0110000 *
b0001000 +
#285
0(
#286
b10011101 #
b00000000000000000000000010010000 %
b1101 &
b1001 '
1(
b0010000 *
b0100001 +
#287
0(
#288
b11001110 #
b00000000000000000000000010010001 %
b1110 &
b1100 '
1(
b1000110 *
b0000110 +
#289
0(
#290
b11100111 #
b00000000000000000000000010010010 %
b0111 &
b1110 '
1(
b0000110 *
b1111000 +
#291
0(
#292
b01110011 #
b00000000000000000000000010010011 %
b0011 &
b0111 '
1(
b1111000 *
b0110000 +
#293
0(
#294
b00111001 #
b00000000000000000000000010010100 %
b1001 &
b0011 '
1(
b0110000 *
b0010000 +
#295
0(
#296
b00011100 #
b00000000000000000000000010010101 %
b1100 &
b0001 '
1(
b1111001 *
b1000110 +
#297
0(
#298
b10001110 #
b00000000000000000000000010010110 %
b1110 &
b1000 '
1(
b0000000 *
b0000110 +
#299
0(
#300
b11000111 #
b00000000000000000000000010010111 %
b0111 &
b1100 '
1(
b1000110 *
b1111000 +
#301
0(
#302
b01100011 #
b00000000000000000000000010011000 %
b0011 &
b0110 '
1(
b0000010 *
b0110000 +
#303
0(
#304
b10110001 #
b00000000000000000000000010011001 %
b0001 &
b1011 '
1(
b0000011 *
b1111001 +
#305
0(
#306
b11011000 #
b00000000000000000000000010011010 %
b1000 &
b1101 '
1(
b0100001 *
b0000000 +
#307
0(
#308
b01101100 #
b00000000000000000000000010011011 %
b1100 &
b0110 '
1(
b0000010 *
b1000110 +
#309
0(
#310
b00110110 #
b00000000000000000000000010011100 %
b0110 &
b0011 '
1(
b0110000 *
b0000010 +
#311
0(
#312
b10011011 #
b00000000000000000000000010011101 %
b1011 &
b1001 '
1(
b0010000 *
b0000011 +
#313
0(
#314
b11001101 #
b00000000000000000000000010011110 %
b1101 &
b1100 '
1(
b1000110 *
b0100001 +
#315
0(
#316
b01100110 #
b00000000000000000000000010011111 %
b0110 &
b0110 '
1(
b0000010 *
b0000010 +
#317
0(
#318
b00110011 #
b00000000000000000000000010100000 %
b0011 &
b0011 '
1(
b0110000 *
b0110000 +
#319
0(
#320
b00011001 #
b00000000000000000000000010100001 %
b1001 &
b0001 '
1(
b1111001 *
b0010000 +
#321
0(
#322
b00001100 #
b00000000000000000000000010100010 %
b1100 &
b0000 '
1(
b1000000 *
b1000110 +
#323
0(
#324
b00000110 #
b00000000000000000000000010100011 %
b0110 &
1(
b0000010 +
#325
0(
#326
b00000011 #
b00000000000000000000000010100100 %
b0011 &
1(
b0110000 +
#327
0(
#328
b10000001 #
b00000000000000000000000010100101 %
b0001 &
b1000 '
1(
b0000000 *
b1111001 +
#329
0(
#330
b01000000 #
b00000000000000000000000010100110 %
b0000 &
b0100 '
1(
b0011001 *
b1000000 +
#331
0(
#332
b00100000 #
b00000000000000000000000010100111 %
b0010 '
1(
b0100100 *
#333
0(
#334
b00010000 #
b00000000000000000000000010101000 %
b0001 '
1(
b1111001 *
#335
0(
#336
b10001000 #
b00000000000000000000000010101001 %
b1000 &
b1000 '
1(
b0000000 *
b0000000 +
#337
0(
#338
b11000100 #
b00000000000000000000000010101010 %
b0100 &
b1100 '
1(
b1000110 *
b0011001 +
#339
0(
#340
b11100010 #
b00000000000000000000000010101011 %
b0010 &
b1110 '
1(
b0000110 *
b0100100 +
#341
0(
#342
b11110001 #
b00000000000000000000000010101100 %
b0001 &
b1111 '
1(
b0001110 *
b1111001 +
#343
0(
#344
b11111000 #
b00000000000000000000000010101101 %
b1000 &
1(
b0000000 +
#345
0(
#346
b01111100 #
b00000000000000000000000010101110 %
b1100 &
b0111 '
1(
b1111000 *
b1000110 +
#347
0(
#348
b10111110 #
b00000000000000000000000010101111 %
b1110 &
b1011 '
1(
b0000011 *
b0000110 +
#349
0(
#350
b01011111 #
b00000000000000000000000010110000 %
b1111 &
b0101 '
1(
b0010010 *
b0001110 +
#351
0(
#352
b00101111 #
b00000000000000000000000010110001 %
b0010 '
1(
b0100100 *
#353
0(
#354
b10010111 #
b00000000000000000000000010110010 %
b0111 &
b1001 '
1(
b0010000 *
b1111000 +
#355
0(
#356
b11001011 #
b00000000000000000000000010110011 %
b1011 &
b1100 '
1(
b1000110 *
b0000011 +
#357
0(
#358
b01100101 #
b00000000000000000000000010110100 %
b0101 &
b0110 '
1(
b0000010 *
b0010010 +
#359
0(
#360
b10110010 #
b00000000000000000000000010110101 %
b0010 &
b1011 '
1(
b0000011 *
b0100100 +
#361
0(
#362
b01011001 #
b00000000000000000000000010110110 %
b1001 &
b0101 '
1(
b0010010 *
b0010000 +
#363
0(
#364
b00101100 #
b00000000000000000000000010110111 %
b1100 &
b0010 '
1(
b0100100 *
b1000110 +
#365
0(
#366
b00010110 #
b00000000000000000000000010111000 %
b0110 &
b0001 '
1(
b1111001 *
b0000010 +
#367
0(
#368
b10001011 #
b00000000000000000000000010111001 %
b1011 &
b1000 '
1(
b0000000 *
b0000011 +
#369
0(
#370
b01000101 #
b00000000000000000000000010111010 %
b0101 &
b0100 '
1(
b0011001 *
b0010010 +
#371
0(
#372
b10100010 #
b00000000000000000000000010111011 %
b0010 &
b1010 '
1(
b0001000 *
b0100100 +
#373
0(
#374
b11010001 #
b00000000000000000000000010111100 %
b0001 &
b1101 '
1(
b0100001 *
b1111001 +
#375
0(
#376
b11101000 #
b00000000000000000000000010111101 %
b1000 &
b1110 '
1(
b0000110 *
b0000000 +
#377
0(
#378
b11110100 #
b00000000000000000000000010111110 %
b0100 &
b1111 '
1(
b0001110 *
b0011001 +
#379
0(
#380
b01111010 #
b00000000000000000000000010111111 %
b1010 &
b0111 '
1(
b1111000 *
b0001000 +
#381
0(
#382
b10111101 #
b00000000000000000000000011000000 %
b1101 &
b1011 '
1(
b0000011 *
b0100001 +
#383
0(
#384
b11011110 #
b00000000000000000000000011000001 %
b1110 &
b1101 '
1(
b0100001 *
b0000110 +
#385
0(
#386
b01101111 #
b00000000000000000000000011000010 %
b1111 &
b0110 '
1(
b0000010 *
b0001110 +
#387
0(
#388
b10110111 #
b00000000000000000000000011000011 %
b0111 &
b1011 '
1(
b0000011 *
b1111000 +
#389
0(
#390
b11011011 #
b00000000000000000000000011000100 %
b1011 &
b1101 '
1(
b0100001 *
b0000011 +
#391
0(
#392
b11101101 #
b00000000000000000000000011000101 %
b1101 &
b1110 '
1(
b0000110 *
b0100001 +
#393
0(
#394
b01110110 #
b00000000000000000000000011000110 %
b0110 &
b0111 '
1(
b1111000 *
b0000010 +
#395
0(
#396
b10111011 #
b00000000000000000000000011000111 %
b1011 &
b1011 '
1(
b0000011 *
b0000011 +
#397
0(
#398
b11011101 #
b00000000000000000000000011001000 %
b1101 &
b1101 '
1(
b0100001 *
b0100001 +
#399
0(
#400
b11101110 #
b00000000000000000000000011001001 %
b1110 &
b1110 '
1(
b0000110 *
b0000110 +
#401
0(
#402
b11110111 #
b00000000000000000000000011001010 %
b0111 &
b1111 '
1(
b0001110 *
b1111000 +
#403
0(
#404
b11111011 #
b00000000000000000000000011001011 %
b1011 &
1(
b0000011 +
#405
0(
#406
b11111101 #
b00000000000000000000000011001100 %
b1101 &
1(
b0100001 +
#407
0(
#408
b11111110 #
b00000000000000000000000011001101 %
b1110 &
1(
b0000110 +
#409
0(
#410
b01111111 #
b00000000000000000000000011001110 %
b1111 &
b0111 '
1(
b1111000 *
b0001110 +
#411
0(
#412
b00111111 #
b00000000000000000000000011001111 %
b0011 '
1(
b0110000 *
#413
0(
#414
b00011111 #
b00000000000000000000000011010000 %
b0001 '
1(
b1111001 *
#415
0(
#416
b00001111 #
b00000000000000000000000011010001 %
b0000 '
1(
b1000000 *
#417
0(
#418
b10000111 #
b00000000000000000000000011010010 %
b0111 &
b1000 '
1(
b0000000 *
b1111000 +
#419
0(
#420
b01000011 #
b00000000000000000000000011010011 %
b0011 &
b0100 '
1(
b0011001 *
b0110000 +
#421
0(
#422
b10100001 #
b00000000000000000000000011010100 %
b0001 &
b1010 '
1(
b0001000 *
b1111001 +
#423
0(
#424
b01010000 #
b00000000000000000000000011010101 %
b0000 &
b0101 '
1(
b0010010 *
b1000000 +
#425
0(
#426
b10101000 #
b00000000000000000000000011010110 %
b1000 &
b1010 '
1(
b0001000 *
b0000000 +
#427
0(
#428
b11010100 #
b00000000000000000000000011010111 %
b0100 &
b1101 '
1(
b0100001 *
b0011001 +
#429
0(
#430
b01101010 #
b00000000000000000000000011011000 %
b1010 &
b0110 '
1(
b0000010 *
b0001000 +
#431
0(
#432
b00110101 #
b00000000000000000000000011011001 %
b0101 &
b0011 '
1(
b0110000 *
b0010010 +
#433
0(
#434
b00011010 #
b00000000000000000000000011011010 %
b1010 &
b0001 '
1(
b1111001 *
b0001000 +
#435
0(
#436
b10001101 #
b00000000000000000000000011011011 %
b1101 &
b1000 '
1(
b0000000 *
b0100001 +
#437
0(
#438
b01000110 #
b00000000000000000000000011011100 %
b0110 &
b0100 '
1(
b0011001 *
b0000010 +
#439
0(
#440
b00100011 #
b00000000000000000000000011011101 %
b0011 &
b0010 '
1(
b0100100 *
b0110000 +
#441
0(
#442
b10010001 #
b00000000000000000000000011011110 %
b0001 &
b1001 '
1(
b0010000 *
b1111001 +
#443
0(
#444
b11001000 #
b00000000000000000000000011011111 %
b1000 &
b1100 '
1(
b1000110 *
b0000000 +
#445
0(
#446
b11100100 #
b00000000000000000000000011100000 %
b0100 &
b1110 '
1(
b0000110 *
b0011001 +
#447
0(
#448
b11110010 #
b00000000000000000000000011100001 %
b0010 &
b1111 '
1(
b0001110 *
b0100100 +
#449
0(
#450
b01111001 #
b00000000000000000000000011100010 %
b1001 &
b0111 '
1(
b1111000 *
b0010000 +
#451
0(
#452
b00111100 #
b00000000000000000000000011100011 %
b1100 &
b0011 '
1(
b0110000 *
b1000110 +
#453
0(
#454
b10011110 #
b00000000000000000000000011100100 %
b1110 &
b1001 '
1(
b0010000 *
b0000110 +
#455
0(
#456
b01001111 #
b00000000000000000000000011100101 %
b1111 &
b0100 '
1(
b0011001 *
b0001110 +
#457
0(
#458
b10100111 #
b00000000000000000000000011100110 %
b0111 &
b1010 '
1(
b0001000 *
b1111000 +
#459
0(
#460
b01010011 #
b00000000000000000000000011100111 %
b0011 &
b0101 '
1(
b0010010 *
b0110000 +
#461
0(
#462
b00101001 #
b00000000000000000000000011101000 %
b1001 &
b0010 '
1(
b0100100 *
b0010000 +
#463
0(
#464
b10010100 #
b00000000000000000000000011101001 %
b0100 &
b1001 '
1(
b0010000 *
b0011001 +
#465
0(
#466
b01001010 #
b00000000000000000000000011101010 %
b1010 &
b0100 '
1(
b0011001 *
b0001000 +
#467
0(
#468
b00100101 #
b00000000000000000000000011101011 %
b0101 &
b0010 '
1(
b0100100 *
b0010010 +
#469
0(
#470
b10010010 #
b00000000000000000000000011101100 %
b0010 &
b1001 '
1(
b0010000 *
b0100100 +
#471
0(
#472
b01001001 #
b00000000000000000000000011101101 %
b1001 &
b0100 '
1(
b0011001 *
b0010000 +
#473
0(
