nju_digital/ex6/generalshifter/top.v
module top (
    input clk,
    input [7:0]din,
    input [2:0]op,
    output reg [7:0]dout8,
    output reg dout1
);
    reg [7:0]temp = 8'b0;
    always@(posedge clk)begin
        case(op)
            3'b000: temp <= 8'b0;
            3'b001: temp <= din;
            3'b010: temp <= {1'b0, temp[7:1]};
            3'b011: temp <= {temp[6:0], 1'b0};
            3'b100: temp <= {temp[7], temp[7:1]};
			3'b101: begin
				dout8 <= temp;
			   	dout1 <= temp[7];
			end
            3'b110: temp <= {temp[0], temp[7:1]};
            3'b111: temp <= {temp[6:0], temp[7]};
            default:temp <= temp;
        endcase
    end

endmodule

nju_digital/ex6/generalshifter/dump.vcd
$version Generated by VerilatedVcd $end
$timescale 1s $end

 $scope module TOP $end
  $var wire  1 # clk $end
  $var wire  8 $ din [7:0] $end
  $var wire  1 ' dout1 $end
  $var wire  8 & dout8 [7:0] $end
  $var wire  3 % op [2:0] $end
  $scope module top $end
   $var wire  1 # clk $end
   $var wire  8 $ din [7:0] $end
   $var wire  1 ' dout1 $end
   $var wire  8 & dout8 [7:0] $end
   $var wire  3 % op [2:0] $end
   $var wire  8 ( temp [7:0] $end
  $upscope $end
 $upscope $end
$enddefinitions $end


#1
0#
b11000110 $
b000 %
b00000000 &
0'
b00000000 (
#2
1#
#3
0#
b001 %
#4
1#
b11000110 (
#5
0#
b010 %
#6
1#
b01100011 (
#7
0#
#8
1#
b00110001 (
#9
0#
b011 %
#10
1#
b01100010 (
#11
0#
#12
1#
b11000100 (
#13
0#
b100 %
#14
1#
b11100010 (
#15
0#
b101 %
#16
1#
b11100010 &
1'
#17
0#
b110 %
#18
1#
b01110001 (
#19
0#
b111 %
#20
1#
b11100010 (
#21
0#
#22
1#
b11000101 (
#23
0#
b101 %
#24
1#
b11000101 &
